happylogging/__init__.py
happylogging/utils.py
happylogging-0.0.4.dist-info/DESCRIPTION.rst
happylogging-0.0.4.dist-info/METADATA
happylogging-0.0.4.dist-info/RECORD
happylogging-0.0.4.dist-info/WHEEL
happylogging-0.0.4.dist-info/metadata.json
happylogging-0.0.4.dist-info/top_level.txt
