Metadata-Version: 2.0
Name: happylogging
Version: 0.0.4
Summary: Utility functions to help using standard logging module.
Home-page: https://github.com/atsuoishimoto/happylogging
Author: Atsuo Ishimoto
Author-email: UNKNOWN
License: MIT
Keywords: logging
Platform: UNKNOWN
Classifier: Programming Language :: Python :: 3.4
Classifier: Programming Language :: Python :: 3.5
Classifier: Development Status :: 5 - Production/Stable
Classifier: License :: OSI Approved :: MIT License
Classifier: Topic :: Software Development :: Libraries :: Python Modules
